pythoncommons/.DS_Store
pythoncommons/__init__.py
pythoncommons/constants.py
pythoncommons/date_utils.py
pythoncommons/docker_wrapper.py
pythoncommons/email.py
pythoncommons/file_parser/__init__.py
pythoncommons/file_parser/input_file_parser.py
pythoncommons/file_parser/parser_config_reader.py
pythoncommons/file_utils.py
pythoncommons/git_constants.py
pythoncommons/git_utils.py
pythoncommons/git_wrapper.py
pythoncommons/github_utils.py
pythoncommons/html_utils.py
pythoncommons/jira_utils.py
pythoncommons/jira_wrapper.py
pythoncommons/logging_setup.py
pythoncommons/logging_utils.py
pythoncommons/network_utils.py
pythoncommons/object_utils.py
pythoncommons/os_utils.py
pythoncommons/patch_utils.py
pythoncommons/process.py
pythoncommons/project_utils.py
pythoncommons/random_utils.py
pythoncommons/result_printer.py
pythoncommons/string_utils.py
pythoncommons/test-input-files/hadoop-git-repo-log.txt
pythoncommons/test-scripts/commands/testcommand/dummy_test_command.py
pythoncommons/test-scripts/download.sh
pythoncommons/test-scripts/hello_world_simple.py
pythoncommons/test-scripts/script_that_fails.sh
pythoncommons/test-scripts/script_with_args.sh
pythoncommons/test-scripts/sleeping_loop.sh
pythoncommons/test-scripts/test_project.py
pythoncommons/test-scripts/utils.sh
pythoncommons/test_utils.py
pythoncommons/tests/__init__.py
pythoncommons/tests/test_docker_wrapper.py
pythoncommons/tests/test_file_utils.py
pythoncommons/tests/test_jira_utils.py
pythoncommons/tests/test_logging_utils.py
pythoncommons/tests/test_process.py
pythoncommons/tests/test_project_utils.py
pythoncommons/url_utils.py
pythoncommons/zip_utils.py
python_common_lib-1.0.18.dist-info/LICENSE
python_common_lib-1.0.18.dist-info/METADATA
python_common_lib-1.0.18.dist-info/WHEEL
python_common_lib-1.0.18.dist-info/RECORD
