Metadata-Version: 2.1
Name: python-common-lib
Version: 1.0.18
Summary: 
Author: Szilard Nemeth
Author-email: szilard.nemeth88@gmail.com
Requires-Python: >=3.9,<4.0
Classifier: Programming Language :: Python :: 3
Classifier: Programming Language :: Python :: 3.9
Classifier: Programming Language :: Python :: 3.10
Classifier: Programming Language :: Python :: 3.11
Classifier: Programming Language :: Python :: 3.12
Requires-Dist: Colr (>=0.9.1,<0.10.0)
Requires-Dist: GitPython (>=3.1.27,<4.0.0)
Requires-Dist: bs4 (>=0.0.1,<0.0.2)
Requires-Dist: dataclasses-json (>=0.5.7,<0.6.0)
Requires-Dist: docker (>=7.1.0,<8.0.0)
Requires-Dist: gspread (>=5.5.0,<6.0.0)
Requires-Dist: humanize (>=4.4.0,<5.0.0)
Requires-Dist: jira (>=3.4.1,<4.0.0)
Requires-Dist: pytest (>=6.2.3,<6.3.0)
Requires-Dist: requests (>=2.28.1,<3.0.0)
Requires-Dist: rich (>=13.7.0,<14.0.0)
Requires-Dist: setuptools (>=75.8.0,<76.0.0)
Requires-Dist: sh (>=1.14.1,<1.15.0)
Requires-Dist: strenum (>=0.4.15,<0.5.0)
Requires-Dist: tabulate (>=0.8.10,<0.9.0)
